annolab/__init__.py
annolab/annolab.py
annolab/annotation.py
annolab/annotation_relation.py
annolab/api_helper.py
annolab/endpoints.py
annolab/project.py
annolab/project_export.py
annolab/project_import.py
annolab/util/__init__.py
annolab/util/cached_property.py
annolab-0.3.3.dist-info/licenses/LICENSE
annolab-0.3.3.dist-info/METADATA
annolab-0.3.3.dist-info/WHEEL
annolab-0.3.3.dist-info/top_level.txt
annolab-0.3.3.dist-info/RECORD
