Metadata-Version: 2.4
Name: annolab
Version: 0.3.3
Summary: Official SDK for the AnnoLab Platform
Home-page: https://github.com/lsimkins/annolab-sdk
Author: AnnoLab
Author-email: luke@annolab.ai
Maintainer: Luke Simkins; Grant DeLozier
License: Apache
Classifier: Development Status :: 3 - Alpha
Classifier: Intended Audience :: Developers
Classifier: Topic :: Software Development :: Build Tools
Classifier: License :: OSI Approved :: MIT License
Classifier: Programming Language :: Python :: 3
Classifier: Programming Language :: Python :: 3.4
Classifier: Programming Language :: Python :: 3.5
Classifier: Programming Language :: Python :: 3.6
Classifier: Programming Language :: Python :: 3.7
License-File: LICENSE
Requires-Dist: requests>=2.25.1
Requires-Dist: polling2>=0.5.0
Requires-Dist: jsonlines>=2.0.0
Dynamic: author
Dynamic: author-email
Dynamic: classifier
Dynamic: description
Dynamic: home-page
Dynamic: license
Dynamic: license-file
Dynamic: maintainer
Dynamic: requires-dist
Dynamic: summary
